nxturtle
ez_setup
